prune_lib/__init__.py
prune_lib/captcha.py
prune_lib/emails.py
prune_lib/geolocalisation.py
prune_lib/logging.py
prune_lib/commons/__init__.py
prune_lib/commons/cache.py
prune_lib/commons/dates.py
prune_lib/commons/decorators.py
prune_lib/commons/email.py
prune_lib/commons/image.py
prune_lib/commons/models.py
prune_lib/commons/parse.py
prune_lib/commons/responses.py
prune_lib/commons/static_finder.py
prune_lib/commons/strings.py
prune_lib/logic/__init__.py
prune_lib/logic/cleaned_data.py
prune_lib/static/prune_lib/css/captcha.css
prune_lib/static/prune_lib/js/captcha.js
prune_lib/templates/prune_lib/captcha.html
prune_lib/templatetags/__init__.py
prune_lib/templatetags/prune_tags.py
prune_lib/website/__init__.py
prune_lib/website/contact.py
prune_lib/website/utils.py
test_project/manage.py
test_project/core/__init__.py
test_project/core/asgi.py
test_project/core/settings.py
test_project/core/urls.py
test_project/core/wsgi.py
test_project/tests/__init__.py
test_project/tests/commons/__init__.py
test_project/tests/commons/test_dates.py
test_project/tests/commons/test_parse.py
test_project/tests/commons/test_strings.py
test_project/tests/logic/__init__.py
test_project/tests/logic/test_cleaned_data.py
test_project/tests/website/__init__.py
test_project/tests/website/test_contact.py
test_project/tests/website/test_utils.py
prune_lib-2.1.5.dist-info/METADATA
prune_lib-2.1.5.dist-info/WHEEL
prune_lib-2.1.5.dist-info/top_level.txt
prune_lib-2.1.5.dist-info/RECORD
