Metadata-Version: 2.4
Name: prune-lib
Version: 2.1.5
Summary: Internal library for prune.sh
Author-email: Arnout <bastien@prune.sh>
Project-URL: Made_by, https://prune.sh/
Keywords: captcha,django,code-quality
Classifier: Programming Language :: Python :: 3
Classifier: License :: OSI Approved :: MIT License
Classifier: Operating System :: OS Independent
Requires-Python: >=3.13
Requires-Dist: build>=1.3.0
Requires-Dist: django>=5.2
Requires-Dist: django-stubs>=5.2.0
Requires-Dist: pillow>=12.0.0
Requires-Dist: pydantic[email]>=2.11.3
Requires-Dist: pytest>=8.4.0
Requires-Dist: sendgrid>=6.11.0
Requires-Dist: twine>=6.1.0
Requires-Dist: ty>=0.0.1a8
